rsmessages/requestFormat.py
rsmessages/responseFormat.py
rsmessages-0.0.2.dist-info/License.txt
rsmessages-0.0.2.dist-info/METADATA
rsmessages-0.0.2.dist-info/WHEEL
rsmessages-0.0.2.dist-info/top_level.txt
rsmessages-0.0.2.dist-info/RECORD
